pdf_notes_extractor/__init__.py
pdf_notes_extractor/analyzer.py
pdf_notes_extractor/cli.py
pdf_notes_extractor/core.py
pdf_notes_extractor/extractors.py
pdf_notes_extractor/models.py
pdf_notes_extractor/output.py
pdf_notes_extractor/patterns.py
pdf_notes_extractor/py.typed
tableta-0.2.1.dist-info/licenses/LICENSE
tableta-0.2.1.dist-info/METADATA
tableta-0.2.1.dist-info/WHEEL
tableta-0.2.1.dist-info/entry_points.txt
tableta-0.2.1.dist-info/top_level.txt
tableta-0.2.1.dist-info/RECORD
