Metadata-Version: 2.4
Name: tableta
Version: 0.2.1
Summary: Extractor de tablas desde notas en PDFs de estados financieros (con detección mejorada)
Author-email: Diego Jiménez <diego.jimenez.g@gmail.com>
License: MIT
Project-URL: Homepage, https://github.com/diegonov1/tableta
Project-URL: Documentation, https://github.com/diegonov1/tableta#readme
Project-URL: Repository, https://github.com/diegonov1/tableta
Project-URL: Bug Tracker, https://github.com/diegonov1/tableta/issues
Keywords: pdf,table-extraction,financial,notes,estados-financieros
Classifier: Development Status :: 4 - Beta
Classifier: Intended Audience :: Developers
Classifier: Intended Audience :: Financial and Insurance Industry
Classifier: License :: OSI Approved :: MIT License
Classifier: Programming Language :: Python :: 3
Classifier: Programming Language :: Python :: 3 :: Only
Classifier: Programming Language :: Python :: 3.8
Classifier: Programming Language :: Python :: 3.9
Classifier: Programming Language :: Python :: 3.10
Classifier: Programming Language :: Python :: 3.11
Classifier: Programming Language :: Python :: 3.12
Classifier: Operating System :: OS Independent
Classifier: Topic :: Office/Business :: Financial
Classifier: Topic :: Text Processing :: General
Classifier: Topic :: Software Development :: Libraries :: Python Modules
Classifier: Typing :: Typed
Requires-Python: >=3.8
License-File: LICENSE
Requires-Dist: pandas>=1.3.0
Requires-Dist: pdfplumber>=0.7.0
Requires-Dist: openpyxl>=3.0.0
Provides-Extra: camelot
Requires-Dist: camelot-py[cv]>=0.11.0; extra == "camelot"
Provides-Extra: tabula
Requires-Dist: tabula-py>=2.5.0; extra == "tabula"
Provides-Extra: all
Requires-Dist: camelot-py[cv]>=0.11.0; extra == "all"
Requires-Dist: tabula-py>=2.5.0; extra == "all"
Provides-Extra: dev
Requires-Dist: pytest>=7.0.0; extra == "dev"
Requires-Dist: pytest-cov>=4.0.0; extra == "dev"
Requires-Dist: black>=22.0.0; extra == "dev"
Requires-Dist: flake8>=5.0.0; extra == "dev"
Requires-Dist: mypy>=1.0.0; extra == "dev"
Requires-Dist: build>=0.10.0; extra == "dev"
Requires-Dist: twine>=4.0.0; extra == "dev"
Dynamic: license-file
